apiutil.py
setup.cfg
setup.py
aiplat.egg-info/PKG-INFO
aiplat.egg-info/SOURCES.txt
aiplat.egg-info/dependency_links.txt
aiplat.egg-info/not-zip-safe
aiplat.egg-info/top_level.txt