Metadata-Version: 1.0
Name: aiplat
Version: 0.0.1
Summary: 腾讯AI开放平台API
Home-page: https://github.com/FloydaGithub/aiplat
Author: Floyda
Author-email: floyda@163.com
License: UNKNOWN
Platform: UNKNOWN
